<annotation><filename>101_03.jpg</filename><folder>example_folder</folder><source><sourceImage>The MIT-CSAIL database of objects and scenes</sourceImage><sourceAnnotation>LabelMe Webtool</sourceAnnotation></source><object><name>ic_1</name><deleted>0</deleted><verified>0</verified><occluded>no</occluded><attributes>3</attributes><parts><hasparts></hasparts><ispartof></ispartof></parts><date>17-Feb-2017 14:15:19</date><id>0</id><type>bounding_box</type><polygon><username>Ramya Rao</username><pt><x>333</x><y>157</y></pt><pt><x>459</x><y>157</y></pt><pt><x>459</x><y>334</y></pt><pt><x>333</x><y>334</y></pt></polygon></object><object><name>ic_2</name><deleted>0</deleted><verified>0</verified><occluded>no</occluded><attributes>2</attributes><parts><hasparts></hasparts><ispartof></ispartof></parts><date>17-Feb-2017 14:15:30</date><id>1</id><type>bounding_box</type><polygon><username>Ramya Rao</username><pt><x>404</x><y>737</y></pt><pt><x>453</x><y>737</y></pt><pt><x>453</x><y>801</y></pt><pt><x>404</x><y>801</y></pt></polygon></object><object><name>ic_3</name><deleted>0</deleted><verified>0</verified><occluded>no</occluded><attributes>1</attributes><parts><hasparts></hasparts><ispartof></ispartof></parts><date>17-Feb-2017 14:15:44</date><id>2</id><type>bounding_box</type><polygon><username>Ramya Rao</username><pt><x>52</x><y>670</y></pt><pt><x>100</x><y>670</y></pt><pt><x>100</x><y>730</y></pt><pt><x>52</x><y>730</y></pt></polygon></object><imagesize><nrows>900</nrows><ncols>1200</ncols></imagesize></annotation>