<annotation><filename>82_42.jpg</filename><folder>example_folder</folder><source><sourceImage>The MIT-CSAIL database of objects and scenes</sourceImage><sourceAnnotation>LabelMe Webtool</sourceAnnotation></source><object><name>ic_1</name><deleted>0</deleted><verified>0</verified><occluded>no</occluded><attributes>3</attributes><parts><hasparts></hasparts><ispartof></ispartof></parts><date>13-Feb-2017 11:29:05</date><id>0</id><type>bounding_box</type><polygon><username>Zhenhua</username><pt><x>754</x><y>156</y></pt><pt><x>871</x><y>156</y></pt><pt><x>871</x><y>408</y></pt><pt><x>754</x><y>408</y></pt></polygon></object><object><name>ic_2</name><deleted>0</deleted><verified>0</verified><occluded>no</occluded><attributes>3</attributes><parts><hasparts></hasparts><ispartof></ispartof></parts><date>13-Feb-2017 11:29:12</date><id>1</id><type>bounding_box</type><polygon><username>Zhenhua</username><pt><x>959</x><y>154</y></pt><pt><x>1075</x><y>154</y></pt><pt><x>1075</x><y>285</y></pt><pt><x>959</x><y>285</y></pt></polygon></object><object><name>ic_3</name><deleted>0</deleted><verified>0</verified><occluded>no</occluded><attributes>3</attributes><parts><hasparts></hasparts><ispartof></ispartof></parts><date>13-Feb-2017 11:29:18</date><id>2</id><type>bounding_box</type><polygon><username>Zhenhua</username><pt><x>1153</x><y>150</y></pt><pt><x>1278</x><y>150</y></pt><pt><x>1278</x><y>283</y></pt><pt><x>1153</x><y>283</y></pt></polygon></object><object><name>ic_4</name><deleted>0</deleted><verified>0</verified><occluded>no</occluded><attributes>3</attributes><parts><hasparts></hasparts><ispartof></ispartof></parts><date>13-Feb-2017 11:29:25</date><id>3</id><type>bounding_box</type><polygon><username>Zhenhua</username><pt><x>1415</x><y>145</y></pt><pt><x>1540</x><y>145</y></pt><pt><x>1540</x><y>381</y></pt><pt><x>1415</x><y>381</y></pt></polygon></object><object><name>ic_5</name><deleted>0</deleted><verified>0</verified><occluded>no</occluded><attributes>3</attributes><parts><hasparts></hasparts><ispartof></ispartof></parts><date>13-Feb-2017 11:29:31</date><id>4</id><type>bounding_box</type><polygon><username>Zhenhua</username><pt><x>748</x><y>508</y></pt><pt><x>881</x><y>508</y></pt><pt><x>881</x><y>748</y></pt><pt><x>748</x><y>748</y></pt></polygon></object><object><name>ic_6</name><deleted>0</deleted><verified>0</verified><occluded>no</occluded><attributes>3</attributes><parts><hasparts></hasparts><ispartof></ispartof></parts><date>13-Feb-2017 11:29:37</date><id>5</id><type>bounding_box</type><polygon><username>Zhenhua</username><pt><x>1036</x><y>504</y></pt><pt><x>1163</x><y>504</y></pt><pt><x>1163</x><y>768</y></pt><pt><x>1036</x><y>768</y></pt></polygon></object><object><name>ic_7</name><deleted>0</deleted><verified>0</verified><occluded>no</occluded><attributes>3</attributes><parts><hasparts></hasparts><ispartof></ispartof></parts><date>13-Feb-2017 11:29:42</date><id>6</id><type>bounding_box</type><polygon><username>Zhenhua</username><pt><x>1219</x><y>502</y></pt><pt><x>1348</x><y>502</y></pt><pt><x>1348</x><y>741</y></pt><pt><x>1219</x><y>741</y></pt></polygon></object><object><name>ic_8</name><deleted>0</deleted><verified>0</verified><occluded>no</occluded><attributes>3</attributes><parts><hasparts></hasparts><ispartof></ispartof></parts><date>13-Feb-2017 11:29:49</date><id>7</id><type>bounding_box</type><polygon><username>Zhenhua</username><pt><x>1385</x><y>504</y></pt><pt><x>1512</x><y>504</y></pt><pt><x>1512</x><y>754</y></pt><pt><x>1385</x><y>754</y></pt></polygon></object><object><name>ic_9</name><deleted>0</deleted><verified>0</verified><occluded>no</occluded><attributes>3</attributes><parts><hasparts></hasparts><ispartof></ispartof></parts><date>13-Feb-2017 11:29:55</date><id>8</id><type>bounding_box</type><polygon><username>Zhenhua</username><pt><x>1594</x><y>500</y></pt><pt><x>1716</x><y>500</y></pt><pt><x>1716</x><y>750</y></pt><pt><x>1594</x><y>750</y></pt></polygon></object><imagesize><nrows>825</nrows><ncols>2122</ncols></imagesize></annotation>