<annotation><filename>84_156.jpg</filename><folder>example_folder</folder><source><sourceImage>The MIT-CSAIL database of objects and scenes</sourceImage><sourceAnnotation>LabelMe Webtool</sourceAnnotation></source><object><name>ic_1</name><deleted>0</deleted><verified>0</verified><occluded>no</occluded><attributes>3</attributes><parts><hasparts></hasparts><ispartof></ispartof></parts><date>08-Feb-2017 20:01:28</date><id>0</id><type>bounding_box</type><polygon><username>Zhenhua</username><pt><x>8</x><y>17</y></pt><pt><x>207</x><y>17</y></pt><pt><x>207</x><y>204</y></pt><pt><x>8</x><y>204</y></pt></polygon></object><object><name>ic_2</name><deleted>0</deleted><verified>0</verified><occluded>no</occluded><attributes>3</attributes><parts><hasparts></hasparts><ispartof></ispartof></parts><date>08-Feb-2017 20:01:51</date><id>1</id><type>bounding_box</type><polygon><username>Zhenhua</username><pt><x>431</x><y>64</y></pt><pt><x>547</x><y>64</y></pt><pt><x>547</x><y>173</y></pt><pt><x>431</x><y>173</y></pt></polygon></object><object><name>ic_3</name><deleted>0</deleted><verified>0</verified><occluded>no</occluded><attributes>3</attributes><parts><hasparts></hasparts><ispartof></ispartof></parts><date>08-Feb-2017 20:02:04</date><id>2</id><type>bounding_box</type><polygon><username>Zhenhua</username><pt><x>372</x><y>224</y></pt><pt><x>532</x><y>224</y></pt><pt><x>532</x><y>369</y></pt><pt><x>372</x><y>369</y></pt></polygon></object><object><name>ic_4</name><deleted>0</deleted><verified>0</verified><occluded>no</occluded><attributes>3</attributes><parts><hasparts></hasparts><ispartof></ispartof></parts><date>08-Feb-2017 20:02:17</date><id>3</id><type>bounding_box</type><polygon><username>Zhenhua</username><pt><x>57</x><y>290</y></pt><pt><x>260</x><y>290</y></pt><pt><x>260</x><y>558</y></pt><pt><x>57</x><y>558</y></pt></polygon></object><object><name>ic_5</name><deleted>0</deleted><verified>0</verified><occluded>no</occluded><attributes>3</attributes><parts><hasparts></hasparts><ispartof></ispartof></parts><date>08-Feb-2017 20:06:23</date><id>4</id><type>bounding_box</type><polygon><username>Zhenhua</username><pt><x>625</x><y>224</y></pt><pt><x>732</x><y>224</y></pt><pt><x>732</x><y>316</y></pt><pt><x>625</x><y>316</y></pt></polygon></object><object><name>ic_6</name><deleted>0</deleted><verified>0</verified><occluded>no</occluded><attributes>3</attributes><parts><hasparts></hasparts><ispartof></ispartof></parts><date>08-Feb-2017 20:06:38</date><id>5</id><type>bounding_box</type><polygon><username>Zhenhua</username><pt><x>513</x><y>481</y></pt><pt><x>748</x><y>481</y></pt><pt><x>748</x><y>576</y></pt><pt><x>513</x><y>576</y></pt></polygon></object><object><name>ic_7</name><deleted>0</deleted><verified>0</verified><occluded>no</occluded><attributes>3</attributes><parts><hasparts></hasparts><ispartof></ispartof></parts><date>08-Feb-2017 20:06:58</date><id>6</id><type>bounding_box</type><polygon><username>Zhenhua</username><pt><x>747</x><y>59</y></pt><pt><x>642</x><y>59</y></pt><pt><x>642</x><y>1</y></pt><pt><x>747</x><y>1</y></pt></polygon></object><imagesize><nrows>768</nrows><ncols>1024</ncols></imagesize></annotation>