<annotation><filename>91_30.jpg</filename><folder>example_folder</folder><source><sourceImage>The MIT-CSAIL database of objects and scenes</sourceImage><sourceAnnotation>LabelMe Webtool</sourceAnnotation></source><object><name>ic_1</name><deleted>0</deleted><verified>0</verified><occluded>no</occluded><attributes>3</attributes><parts><hasparts></hasparts><ispartof></ispartof></parts><date>10-Feb-2017 19:51:54</date><id>0</id><type>bounding_box</type><polygon><username>lewisber</username><pt><x>439</x><y>73</y></pt><pt><x>478</x><y>73</y></pt><pt><x>478</x><y>118</y></pt><pt><x>439</x><y>118</y></pt></polygon></object><object><name>ic_2</name><deleted>0</deleted><verified>0</verified><occluded>no</occluded><attributes>2</attributes><parts><hasparts></hasparts><ispartof></ispartof></parts><date>10-Feb-2017 19:52:05</date><id>1</id><type>bounding_box</type><polygon><username>lewisber</username><pt><x>497</x><y>104</y></pt><pt><x>525</x><y>104</y></pt><pt><x>525</x><y>129</y></pt><pt><x>497</x><y>129</y></pt></polygon></object><object><name>ic_3</name><deleted>0</deleted><verified>0</verified><occluded>no</occluded><attributes>3</attributes><parts><hasparts></hasparts><ispartof></ispartof></parts><date>10-Feb-2017 19:52:18</date><id>2</id><type>bounding_box</type><polygon><username>lewisber</username><pt><x>152</x><y>81</y></pt><pt><x>194</x><y>81</y></pt><pt><x>194</x><y>122</y></pt><pt><x>152</x><y>122</y></pt></polygon></object><object><name>ic_4</name><deleted>0</deleted><verified>0</verified><occluded>no</occluded><attributes>3</attributes><parts><hasparts></hasparts><ispartof></ispartof></parts><date>10-Feb-2017 19:52:35</date><id>3</id><type>bounding_box</type><polygon><username>lewisber</username><pt><x>560</x><y>247</y></pt><pt><x>604</x><y>247</y></pt><pt><x>604</x><y>287</y></pt><pt><x>560</x><y>287</y></pt></polygon></object><object><name>ic_5</name><deleted>0</deleted><verified>0</verified><occluded>no</occluded><attributes>2</attributes><parts><hasparts></hasparts><ispartof></ispartof></parts><date>10-Feb-2017 19:52:52</date><id>4</id><type>bounding_box</type><polygon><username>lewisber</username><pt><x>771</x><y>281</y></pt><pt><x>793</x><y>281</y></pt><pt><x>793</x><y>310</y></pt><pt><x>771</x><y>310</y></pt></polygon></object><object><name>ic_6</name><deleted>0</deleted><verified>0</verified><occluded>yes</occluded><attributes>2</attributes><parts><hasparts></hasparts><ispartof></ispartof></parts><date>10-Feb-2017 19:53:07</date><id>5</id><type>bounding_box</type><polygon><username>lewisber</username><pt><x>770</x><y>240</y></pt><pt><x>792</x><y>240</y></pt><pt><x>792</x><y>268</y></pt><pt><x>770</x><y>268</y></pt></polygon></object><object><name>ic_7</name><deleted>0</deleted><verified>0</verified><occluded>no</occluded><attributes>3</attributes><parts><hasparts></hasparts><ispartof></ispartof></parts><date>10-Feb-2017 19:53:32</date><id>6</id><type>bounding_box</type><polygon><username>lewisber</username><pt><x>1118</x><y>523</y></pt><pt><x>1154</x><y>523</y></pt><pt><x>1154</x><y>558</y></pt><pt><x>1118</x><y>558</y></pt></polygon></object><object><name>ic_8</name><deleted>0</deleted><verified>0</verified><occluded>no</occluded><attributes>2</attributes><parts><hasparts></hasparts><ispartof></ispartof></parts><date>10-Feb-2017 19:53:51</date><id>7</id><type>bounding_box</type><polygon><username>lewisber</username><pt><x>540</x><y>720</y></pt><pt><x>569</x><y>720</y></pt><pt><x>569</x><y>743</y></pt><pt><x>540</x><y>743</y></pt></polygon></object><object><name>ic_9</name><deleted>0</deleted><verified>0</verified><occluded>no</occluded><attributes>3</attributes><parts><hasparts></hasparts><ispartof></ispartof></parts><date>10-Feb-2017 19:54:04</date><id>8</id><type>bounding_box</type><polygon><username>lewisber</username><pt><x>494</x><y>811</y></pt><pt><x>534</x><y>811</y></pt><pt><x>534</x><y>854</y></pt><pt><x>494</x><y>854</y></pt></polygon></object><object><name>ic_10</name><deleted>0</deleted><verified>0</verified><occluded>no</occluded><attributes>3</attributes><parts><hasparts></hasparts><ispartof></ispartof></parts><date>10-Feb-2017 19:54:18</date><id>9</id><type>bounding_box</type><polygon><username>lewisber</username><pt><x>351</x><y>808</y></pt><pt><x>446</x><y>808</y></pt><pt><x>446</x><y>885</y></pt><pt><x>351</x><y>885</y></pt></polygon></object><object><name>ic_11</name><deleted>0</deleted><verified>0</verified><occluded>no</occluded><attributes>3</attributes><parts><hasparts></hasparts><ispartof></ispartof></parts><date>10-Feb-2017 19:54:37</date><id>10</id><type>bounding_box</type><polygon><username>lewisber</username><pt><x>196</x><y>549</y></pt><pt><x>235</x><y>549</y></pt><pt><x>235</x><y>593</y></pt><pt><x>196</x><y>593</y></pt></polygon></object><imagesize><nrows>988</nrows><ncols>1200</ncols></imagesize></annotation>